netbox_netauto_plugin/__init__.py
netbox_netauto_plugin/choices.py
netbox_netauto_plugin/filtersets.py
netbox_netauto_plugin/forms.py
netbox_netauto_plugin/models.py
netbox_netauto_plugin/navigation.py
netbox_netauto_plugin/signals.py
netbox_netauto_plugin/tables.py
netbox_netauto_plugin/urls.py
netbox_netauto_plugin/utils.py
netbox_netauto_plugin/validators.py
netbox_netauto_plugin/views.py
netbox_netauto_plugin/api/__init__.py
netbox_netauto_plugin/api/serializers.py
netbox_netauto_plugin/api/urls.py
netbox_netauto_plugin/api/views.py
netbox_netauto_plugin/migrations/0001_initial.py
netbox_netauto_plugin/migrations/0002_alter_flexapplication_dst_address_l4application_and_more.py
netbox_netauto_plugin/migrations/0003_alter_flexapplication_health_monitor_and_more.py
netbox_netauto_plugin/migrations/0004_flexapplication_dst_address_string_and_more.py
netbox_netauto_plugin/migrations/0005_alter_flexapplication_dst_address_string_and_more.py
netbox_netauto_plugin/migrations/0006_flexapplication_cluster_flexapplication_ritm_and_more.py
netbox_netauto_plugin/migrations/0007_alter_flexapplication_cluster_and_more.py
netbox_netauto_plugin/migrations/0008_alter_flexapplication_health_monitor_and_more.py
netbox_netauto_plugin/migrations/0009_alter_flexapplication_health_monitor_and_more.py
netbox_netauto_plugin/migrations/0010_rename_dst_address_flexapplication_virtual_ip_address_and_more.py
netbox_netauto_plugin/migrations/0011_remove_l4application_health_monitor_and_more.py
netbox_netauto_plugin/migrations/0012_alter_flexapplication_interval_and_more.py
netbox_netauto_plugin/migrations/0013_alter_flexapplication_client_ssl_profile_and_more.py
netbox_netauto_plugin/migrations/0014_alter_profile_options_alter_flexapplication_tcp_wan_and_more.py
netbox_netauto_plugin/migrations/0015_alter_flexapplication_health_monitor_profile_and_more.py
netbox_netauto_plugin/migrations/0016_remove_l4application_health_monitor_profile_and_more.py
netbox_netauto_plugin-1.0.6.dist-info/LICENSE
netbox_netauto_plugin-1.0.6.dist-info/METADATA
netbox_netauto_plugin-1.0.6.dist-info/WHEEL
netbox_netauto_plugin-1.0.6.dist-info/top_level.txt
netbox_netauto_plugin-1.0.6.dist-info/RECORD
