Metadata-Version: 2.1
Name: netbox-netauto-plugin
Version: 1.0.6
Summary: NetBox plugin for integration with the netauto ecosystem.
Author: Matej Lanca
Author-email: lancamatej@gmail.com
Classifier: Programming Language :: Python :: 3
Classifier: License :: OSI Approved :: MIT License
Classifier: Operating System :: OS Independent
Requires-Python: >=3.9
License-File: LICENSE
